README.md
setup.py
src/sentry_dingding_gio/__init__.py
src/sentry_dingding_gio/forms.py
src/sentry_dingding_gio/plugin.py
src/sentry_dingding_gio.egg-info/PKG-INFO
src/sentry_dingding_gio.egg-info/SOURCES.txt
src/sentry_dingding_gio.egg-info/dependency_links.txt
src/sentry_dingding_gio.egg-info/entry_points.txt
src/sentry_dingding_gio.egg-info/not-zip-safe
src/sentry_dingding_gio.egg-info/requires.txt
src/sentry_dingding_gio.egg-info/top_level.txt