Metadata-Version: 2.1
Name: sentry-dingding-gio
Version: 0.0.1
Summary: A Sentry extension which send errors stats to DingDing
Home-page: https://www.growingio.com
Author: howard
Author-email: nocturne2023@gmail.com
License: MIT
Keywords: sentry dingding
Platform: UNKNOWN
Classifier: Programming Language :: Python :: 2.7
Classifier: License :: OSI Approved :: MIT License
